socketssh/__init__.py
socketssh/client.py
socketssh/interface.py
socketssh/server.py
socketssh-1.0.5.dist-info/METADATA
socketssh-1.0.5.dist-info/RECORD
socketssh-1.0.5.dist-info/WHEEL
socketssh-1.0.5.dist-info/entry_points.txt
socketssh-1.0.5.dist-info/top_level.txt
