Metadata-Version: 2.1
Name: socketssh
Version: 1.0.5
Summary: The C/S architecture controls the SSH client for a long time
Home-page: https://github.com/578010377/PythonScript/tree/master/socketssh
Author: Jiegl
Author-email: jiegl1@lenovo.com
License: UNKNOWN
Platform: UNKNOWN
Classifier: Programming Language :: Python :: 2
Classifier: Programming Language :: Python :: 3
Classifier: License :: OSI Approved :: MIT License
Classifier: Operating System :: OS Independent
Requires-Dist: pika
